discord/ext/context/__init__.py
discord/ext/context/client.py
discord/ext/context/context.py
discord/ext/context/hooks.py
discord/ext/context/types.py
discord.ext.context-0.1.6.dist-info/LICENSE
discord.ext.context-0.1.6.dist-info/WHEEL
discord.ext.context-0.1.6.dist-info/METADATA
discord.ext.context-0.1.6.dist-info/RECORD
